pexpect_serial_terminal/__init__.py
pexpect_serial_terminal/__main__.py
pexpect_serial_terminal/_version.py
pexpect_serial_terminal/serial_terminal.py
pexpect_serial_terminal-0.5.2.dist-info/LICENSE
pexpect_serial_terminal-0.5.2.dist-info/METADATA
pexpect_serial_terminal-0.5.2.dist-info/WHEEL
pexpect_serial_terminal-0.5.2.dist-info/top_level.txt
pexpect_serial_terminal-0.5.2.dist-info/RECORD
