Metadata-Version: 2.1
Name: pexpect-serial-terminal
Version: 0.5.2
Summary: serial terminal for pexpect on both windows and linux platforms
Home-page: https://github.com/angryisland/pexpect-serial-terminal
Author: Johnny Chiang
Author-email: johnny641119@gmail.com
License: MIT License
Platform: UNKNOWN
Classifier: Programming Language :: Python :: 3
Classifier: License :: OSI Approved :: MIT License
Classifier: Operating System :: OS Independent
Requires-Python: >=3.0
Requires-Dist: pyserial
